previsionio/__init__.py
previsionio/_version.py
previsionio/api_resource.py
previsionio/connector.py
previsionio/dataset.py
previsionio/datasource.py
previsionio/deployed_model.py
previsionio/experiment.py
previsionio/experiment_config.py
previsionio/experiment_deployment.py
previsionio/experiment_version.py
previsionio/export.py
previsionio/exporter.py
previsionio/external_experiment_version.py
previsionio/logger.py
previsionio/metrics.py
previsionio/model.py
previsionio/pipeline.py
previsionio/prediction.py
previsionio/prevision_client.py
previsionio/project.py
previsionio/supervised.py
previsionio/text_similarity.py
previsionio/timeseries.py
previsionio/utils.py
previsionio-12.0.0.dist-info/LICENSE
previsionio-12.0.0.dist-info/LICENSE_NUMPY
previsionio-12.0.0.dist-info/LICENSE_OAUTHLIB
previsionio-12.0.0.dist-info/LICENSE_PANDAS
previsionio-12.0.0.dist-info/LICENSE_PYFLAKES
previsionio-12.0.0.dist-info/LICENSE_REQUESTS
previsionio-12.0.0.dist-info/METADATA
previsionio-12.0.0.dist-info/WHEEL
previsionio-12.0.0.dist-info/top_level.txt
previsionio-12.0.0.dist-info/RECORD
