Metadata-Version: 2.1
Name: previsionio
Version: 12.0.0
Summary: python wrapper for prevision api
Home-page: https://github.com/previsionio/prevision-python
Author: prevision.io
Author-email: team-core@prevision.io
License: MIT License
Project-URL: Bug Tracker, https://github.com/previsionio/prevision-python/issues
Project-URL: Documentation, https://prevision-python.readthedocs.io/en/latest/
Project-URL: Source Code, https://github.com/previsionio/prevision-python
Keywords: ml,ai,prevision,sdk
Platform: UNKNOWN
Classifier: Intended Audience :: Developers
Classifier: Natural Language :: English
Classifier: License :: OSI Approved :: MIT License
Classifier: Programming Language :: Python :: 3
Classifier: Programming Language :: Python :: 3.6
Classifier: Programming Language :: Python :: 3.7
Classifier: Programming Language :: Python :: 3.8
Classifier: Programming Language :: Python :: 3.9
Requires-Python: >= 3.6
Requires-Dist: pandas (>=0.25.3)
Requires-Dist: requests (>=2.23.0)
Requires-Dist: numpy (>=1.18.4)
Requires-Dist: requests-oauthlib (>=1.3.0)
Requires-Dist: oauthlib (>=3.1.0)
Requires-Dist: requests-toolbelt (==0.9.1)
